pygl_tetrix/__init__.py
pygl_tetrix/__main__.py
pygl_tetrix/colors.py
pygl_tetrix/controller.py
pygl_tetrix/grid.py
pygl_tetrix/labels.py
pygl_tetrix/piece.py
pygl_tetrix/ptypes.py
pygl_tetrix/square.py
pygl_tetrix/trxconst.py
PyGL_Tetrix-0.0.2.dist-info/LICENSE
PyGL_Tetrix-0.0.2.dist-info/METADATA
PyGL_Tetrix-0.0.2.dist-info/WHEEL
PyGL_Tetrix-0.0.2.dist-info/top_level.txt
PyGL_Tetrix-0.0.2.dist-info/RECORD
