Metadata-Version: 2.1
Name: PyGL-Tetrix
Version: 0.0.2
Summary: One-day Tetris programming challenge using pyglet
Home-page: https://github.com/Woldstn/PyGL-Tetrix
Author: Zach Pierog
Author-email: woldstn@live.com
License: UNKNOWN
Project-URL: Bug Tracker, https://github.com/Woldstn/PyGL-Tetrix/issues
Platform: UNKNOWN
Classifier: Programming Language :: Python :: 3
Classifier: License :: OSI Approved :: MIT License
Classifier: Operating System :: OS Independent
Requires-Python: >=3.6
License-File: LICENSE
Requires-Dist: pyglet
